CHANGES.rst
MANIFEST.in
README.rst
setup.py
tomcom/__init__.py
tomcom.content.tccontentreference.egg-info/PKG-INFO
tomcom.content.tccontentreference.egg-info/SOURCES.txt
tomcom.content.tccontentreference.egg-info/dependency_links.txt
tomcom.content.tccontentreference.egg-info/entry_points.txt
tomcom.content.tccontentreference.egg-info/namespace_packages.txt
tomcom.content.tccontentreference.egg-info/not-zip-safe
tomcom.content.tccontentreference.egg-info/requires.txt
tomcom.content.tccontentreference.egg-info/top_level.txt
tomcom/content/__init__.py
tomcom/content/tccontentreference/__init__.py
tomcom/content/tccontentreference/config.py
tomcom/content/tccontentreference/configure.zcml
tomcom/content/tccontentreference/profiles.zcml
tomcom/content/tccontentreference/tccontentreference.py
tomcom/content/tccontentreference/browser/__init__.py
tomcom/content/tccontentreference/browser/configure.zcml
tomcom/content/tccontentreference/browser/tccontentreference/__init__.py
tomcom/content/tccontentreference/browser/tccontentreference/browser.py
tomcom/content/tccontentreference/browser/tccontentreference/configure.zcml
tomcom/content/tccontentreference/profiles/default/factorytool.xml
tomcom/content/tccontentreference/profiles/default/types.xml
tomcom/content/tccontentreference/profiles/default/types/TCContentReference.xml
tomcom/content/tccontentreference/resource/img/tccontentreference.png
tomcom/content/tccontentreference/templates/__init__.py
tomcom/content/tccontentreference/templates/tccontentreference_relations_overview.pt
tomcom/content/tccontentreference/templates/tccontentreference_view.pt